genai_evaluation/__init__.py
genai_evaluation/genai_evaluation.py
genai_evaluation-0.1.5.dist-info/AUTHORS.rst
genai_evaluation-0.1.5.dist-info/LICENSE
genai_evaluation-0.1.5.dist-info/METADATA
genai_evaluation-0.1.5.dist-info/WHEEL
genai_evaluation-0.1.5.dist-info/top_level.txt
genai_evaluation-0.1.5.dist-info/RECORD
