Metadata-Version: 2.1
Name: genai-evaluation
Version: 0.1.5
Summary: Evaluation of Generative AI Models
Home-page: https://github.com/rajiviyer/genai_evaluation
Author: Rajiv Iyer
Author-email: raju.rgi@gmail.com
License: MIT license
Keywords: genai_evaluation
Classifier: Development Status :: 2 - Pre-Alpha
Classifier: Intended Audience :: Developers
Classifier: License :: OSI Approved :: MIT License
Classifier: Natural Language :: English
Classifier: Programming Language :: Python :: 3
Classifier: Programming Language :: Python :: 3.6
Classifier: Programming Language :: Python :: 3.7
Classifier: Programming Language :: Python :: 3.8
Requires-Python: >=3.6
License-File: LICENSE
License-File: AUTHORS.rst
